{
  "en": "PMMA",
  "cn": "聚甲基丙烯酸甲酯",
  "collected_at": "2026-06-09 15:36",
  "count": 5,
  "companies": [
    {
      "name": "苏州双象光学材料有限公司",
      "credit_code": "91320592592507699G",
      "legal_person": "董文天",
      "reg_capital": "21000万元",
      "established": "2012-03-13",
      "status": "在业",
      "scope": "聚甲基丙烯酸甲酯树脂（PMMA）的制造、加工、销售，化工原料及产品（危险化学品除外）的销售，货物或技术进出口（国家禁止或涉及行政审批的货物和技术进出口除外）。（依法须经批准的项目，经相关部门批准后方可开展经营活动）",
      "province": "江苏",
      "city": "",
      "address": "江苏扬子江化学工业园东海路18号",
      "industry": "初级形态塑料及合成树脂制造",
      "_qcc_industry": "初级形态塑料及合成树脂制造",
      "patent_count": 0,
      "has_chem_patent": false
    },
    {
      "name": "伊春众盛有机玻璃制造有限公司",
      "credit_code": "91230705MA1BEFKJ9J",
      "legal_person": "杜恒梅",
      "reg_capital": "500万元",
      "established": "2019-01-02",
      "status": "存续",
      "scope": "初级形态塑料及合成树脂制造（有机玻璃）；非金属废料和碎屑加工处理",
      "province": "黑龙江",
      "city": "",
      "address": "黑龙江省伊春市西林区白林工业园区原七零七地质队办公室",
      "industry": "初级形态塑料及合成树脂制造",
      "_qcc_industry": "初级形态塑料及合成树脂制造",
      "patent_count": 0,
      "has_chem_patent": false
    },
    {
      "name": "江门市国祥亚克力板材有限公司",
      "credit_code": "91440703MA530L4F4B",
      "legal_person": "蔡以余",
      "reg_capital": "200万元",
      "established": "2019-03-18",
      "status": "在业",
      "scope": "生产、加工、零售：亚克力板材，塑料制品（不含荷塘镇建设项目环保准入负面清单禁止准入类项目）。（依法须经批准的项目，经相关部门批准后方可开展经营活动）",
      "province": "广东",
      "city": "",
      "address": "江门市蓬江区荷塘镇三丫新村二巷6号厂房",
      "industry": "塑料制品业",
      "_qcc_industry": "塑料制品业"
    },
    {
      "name": "江苏绿源璐彩亚克力板材有限公司",
      "credit_code": "91320623071047789B",
      "legal_person": "周兆敏",
      "reg_capital": "2000万元",
      "established": "2013-06-18",
      "status": "存续",
      "scope": "亚克力板材、亚克力洁具板生产、销售；装潢材料、化工原料及产品（危险化学品除外）、金属材料（贵金属除外）、橡塑制品、五金交电、机电设备、纺织品批发、零售；货物和技术的进出口业务（国家限定公司经营或禁止进出口的商品及技术除外）；电子产品、新能源材料、节能环保材料销售；广告设计、制作、发布；展览展示服务；电脑图文的设计、制作；文化艺术交流活动策划。（依法须经批准的项目，经相关部门批准后方可开展经营活动）一般项目：非居住房地产租赁；机械设备租赁；热力生产和供应（除依法须经批准的项目外，凭营业执照依法自主开展经营活动）",
      "province": "江苏",
      "city": "",
      "address": "如东经济开发区新区金沙江路南侧",
      "industry": "建筑装饰材料批发",
      "_qcc_industry": "建筑装饰材料批发"
    },
    {
      "name": "万华化学集团股份有限公司",
      "credit_code": "91370000163044841F",
      "legal_person": "廖增太",
      "reg_capital": "313047.1626万元",
      "established": "1998-12-16",
      "status": "存续",
      "scope": "许可项目：危险化学品生产；危险化学品经营；食品添加剂生产；危险化学品仓储。（依法须经批准的项目，经相关部门批准后方可开展经营活动，具体经营项目以相关部门批准文件或许可证件为准）一般项目：日用化学产品制造；日用化学产品销售；化工产品生产（不含许可类化工产品）；化工产品销售（不含许可类化工产品）；专用化学产品制造（不含危险化学品）；专用化学产品销售（不含危险化学品）；基础化学原料制造（不含危险化学品等许可类化学品的制造）；合成材料制造（不含危险化学品）；合成材料销售；涂料制造（不含危险化学品）；涂料销售（不含危险化学品）；新材料技术研发；生物基材料制造；生物基材料销售；普通货物仓储服务（不含危险化学品等需许可审批的项目）；高性能纤维及复合材料制造；高性能纤维及复合材料销售；石油制品销售（不含危险化学品）；新型催化材料及助剂销售；食品添加剂销售；铁路运输辅助活动；货物进出口；技术进出口；技术服务、技术开发、技术咨询、技术交流、技术转让、技术推广。（除依法须经批准的项目外，凭营业执照依法自主开展经营活动）",
      "province": "山东",
      "city": "",
      "address": "山东省烟台市经济技术开发区重庆大街59号",
      "industry": "有机化学原料制造",
      "_source": "seed"
    }
  ]
}