{
  "en": "PSU",
  "cn": "聚砜",
  "collected_at": "2026-06-10 14:01",
  "count": 3,
  "companies": [
    {
      "name": "大连聚砜塑料有限公司",
      "credit_code": "91210211702174136A",
      "legal_person": "关宏宇",
      "reg_capital": "790万元",
      "established": "1998-03-30",
      "status": "存续",
      "scope": "一般项目：塑料制品制造，工程塑料及合成树脂制造，塑料制品销售，工程塑料及合成树脂销售，合成材料制造（不含危险化学品），合成材料销售，塑料加工专用设备销售，化工产品生产（不含许可类化工产品），化工产品销售（不含许可类化工产品），技术服务、技术开发、技术咨询、技术交流、技术转让、技术推广，金属材料销售，五金产品批发，国内贸易代理（除依法须经批准的项目外，凭营业执照依法自主开展经营活动）",
      "province": "辽宁",
      "city": "",
      "address": "辽宁省大连市甘井子区辛寨子街道砬子山村",
      "industry": "初级形态塑料及合成树脂制造",
      "_qcc_industry": "初级形态塑料及合成树脂制造",
      "patent_count": 0,
      "has_chem_patent": false
    },
    {
      "name": "威海帕斯砜新材料有限公司",
      "credit_code": "91371083493510577Q",
      "legal_person": "王盈盈",
      "reg_capital": "7000万元",
      "established": "2014-04-08",
      "status": "在业",
      "scope": "聚砜新材料及其产品、高分子材料、产业用纺织制品研发、生产、销售；高分子材料、塑料制品、化工产品及原料（不含危险化学品、监控化学品、烟花爆竹、民用爆炸物、易制毒化学品）、仪器仪表的销售；从事高分子材料技术领域内的技术开发、技术转让、技术咨询、技术服务；备案范围内的货物及技术的进出口业务。（依法须经批准的项目，经相关部门批准后方可开展经营活动）。（依法须经批准的项目，经相关部门批准后方可开展经营活动）",
      "province": "山东",
      "city": "",
      "address": "山东省威海市乳山市银滩经济开发区台湾东路26号",
      "industry": "其他建筑材料制造",
      "_qcc_industry": "其他建筑材料制造",
      "patent_count": 0,
      "has_chem_patent": false
    },
    {
      "name": "山西湖大特塑新材科技有限公司",
      "credit_code": "91140329MACGGFK92M",
      "legal_person": "向家勇",
      "reg_capital": "6190.8466万元",
      "established": "2023-04-20",
      "status": "存续",
      "scope": "一般项目：化工产品生产（不含许可类化工产品）；化工产品销售（不含许可类化工产品）；高性能纤维及复合材料制造；高性能纤维及复合材料销售；合成材料制造（不含危险化学品）；合成材料销售；技术服务、技术开发、技术咨询、技术交流、技术转让、技术推广；新型催化材料及助剂销售；新材料技术研发；新材料技术推广服务；工程塑料及合成树脂制造；工程塑料及合成树脂销售；货物进出口；技术进出口。（除依法须经批准的项目外，凭营业执照依法自主开展经营活动）",
      "province": "山西",
      "city": "",
      "address": "山西省阳泉市平定县龙川化工园区",
      "industry": "其他合成材料制造",
      "_qcc_industry": "其他合成材料制造",
      "patent_count": 0,
      "has_chem_patent": false
    }
  ]
}